kamu/__init__.py
kamu/_connection.py
kamu/_connection_flight_sql.py
kamu/_connection_livy.py
kamu/_connection_subprocess.py
kamu/_jupyter.py
kamu/utils.py
kamu-0.7.0.dist-info/LICENSE
kamu-0.7.0.dist-info/METADATA
kamu-0.7.0.dist-info/WHEEL
kamu-0.7.0.dist-info/top_level.txt
kamu-0.7.0.dist-info/RECORD
