Metadata-Version: 2.2
Name: kamu
Version: 0.7.0
Summary: Kamu decentralized data supply chain client library
Author-email: "Kamu Data Inc." <dev@kamu.dev>
License:                                  Apache License
Project-URL: Homepage, https://kamu.dev
Project-URL: Documentation, https://docs.kamu.dev
Project-URL: Repository, https://github.com/kamu-data/kamu-client-python
Project-URL: Issues, https://github.com/kamu-data/kamu-client-python/issues
Project-URL: Changelog, https://github.com/kamu-data/kamu-client-python/blob/master/CHANGELOG.md
Keywords: kamu,opendatafabric,data,decentralized,web3,AI,ML
Classifier: License :: OSI Approved :: Apache Software License
Classifier: Programming Language :: Python
Classifier: Programming Language :: Python :: 3
Requires-Python: >=3.10
License-File: LICENSE
Requires-Dist: adbc_driver_manager
Requires-Dist: adbc_driver_flightsql
Requires-Dist: pyarrow
Provides-Extra: jupyter-autoviz
Requires-Dist: autovizwidget; extra == "jupyter-autoviz"
Provides-Extra: jupyter-sql
Provides-Extra: spark
Requires-Dist: livy; extra == "spark"
Provides-Extra: dev
Requires-Dist: black; extra == "dev"
Requires-Dist: build; extra == "dev"
Requires-Dist: flake8; extra == "dev"
Requires-Dist: isort; extra == "dev"
Requires-Dist: pandas; extra == "dev"
Requires-Dist: pip-tools; extra == "dev"
Requires-Dist: pylint; extra == "dev"
Requires-Dist: pytest; extra == "dev"
Requires-Dist: twine; extra == "dev"
